setup.cfg
setup.py
./.gitignore
./CHANGES.md
./LICENSE
./README.md
./setup.cfg
./setup.py
./django_last_social_activity.egg-info/PKG-INFO
./django_last_social_activity.egg-info/SOURCES.txt
./django_last_social_activity.egg-info/dependency_links.txt
./django_last_social_activity.egg-info/requires.txt
./django_last_social_activity.egg-info/top_level.txt
./last_social_activity/templates/last_social_activity/social_networks/facebook.html
./last_social_activity/templates/last_social_activity/social_networks/fivehundred.html
./last_social_activity/templates/last_social_activity/social_networks/flickr.html
./last_social_activity/templates/last_social_activity/social_networks/instagram.html
./last_social_activity/templates/last_social_activity/social_networks/pinterest.html
./last_social_activity/templates/last_social_activity/social_networks/rss.html
./last_social_activity/templates/last_social_activity/social_networks/twitter.html
django_last_social_activity.egg-info/PKG-INFO
django_last_social_activity.egg-info/SOURCES.txt
django_last_social_activity.egg-info/dependency_links.txt
django_last_social_activity.egg-info/requires.txt
django_last_social_activity.egg-info/top_level.txt
last_social_activity/__init__.py
last_social_activity/models.py
last_social_activity/migrations/0001_initial.py
last_social_activity/migrations/0002_auto_20170201_1406.py
last_social_activity/migrations/__init__.py
last_social_activity/social_networks/__init__.py
last_social_activity/social_networks/facebook.py
last_social_activity/social_networks/fiveHundred.py
last_social_activity/social_networks/flickr.py
last_social_activity/social_networks/instagram.py
last_social_activity/social_networks/pinterest.py
last_social_activity/social_networks/rss.py
last_social_activity/social_networks/twitter.py
last_social_activity/templatetags/__init__.py
last_social_activity/templatetags/last_social_activity.py