Metadata-Version: 1.1
Name: django-last-social-activity
Version: 0.2.1
Summary: A simple application for Django to fetch the last posts of your social network profiles in your site.
Home-page: https://github.com/intelligenia/django-last-social-activity
Author: intelligenia S.L.
Author-email: diego@intelligenia.es
License: MIT
Keywords: simple social networks integration wall tweet facebook twitter instagram pinterest rss
Platform: UNKNOWN
Classifier: Development Status :: 5 - Production/Stable
Classifier: Framework :: Django
Classifier: License :: OSI Approved :: MIT License
